DSCO-3/Lab2/Q2/q2/q2i.v
module q2i(x, y, z, F);
    input x, y, z;
    output F;
    nor(X, x, x);
    nor(XZ, X, z);
    nor(f, XZ, y);
    nor(F, f, f);
endmodule

DSCO-3/Lab2/Q2/q2/q2i_tb.v
`timescale 1ns/1ns
`include "q2i.v"

module q2i_tb();
reg x, y, z;
wire F;

q2i Q2i(x, y, z, F);
initial
begin

    $dumpfile("q2i_tb.vcd");
    $dumpvars(0, q2i_tb);

    x=1'b0; y=1'b0; z=1'b0;
    #20;

    x=1'b0; y=1'b0; z=1'b1;
    #20;

    x=1'b0; y=1'b1; z=1'b0;
    #20;

    x=1'b0; y=1'b1; z=1'b1;
    #20;

    x=1'b1; y=1'b0; z=1'b0;
    #20;

    x=1'b1; y=1'b0; z=1'b1;
    #20;

    x=1'b1; y=1'b1; z=1'b0;
    #20;

    x=1'b1; y=1'b1; z=1'b1;
    #20;

    $display("Test complete");
end

endmodule

DSCO-3/Lab2/Q2/q2/q2i_tb.vcd
$date
	Sat Sep  3 15:37:01 2022
$end
$version
	Icarus Verilog
$end
$timescale
	1ns
$end
$scope module q2i_tb $end
$var wire 1 ! F $end
$var reg 1 " x $end
$var reg 1 # y $end
$var reg 1 $ z $end
$scope module Q2i $end
$var wire 1 ! F $end
$var wire 1 % X $end
$var wire 1 & XZ $end
$var wire 1 ' f $end
$var wire 1 " x $end
$var wire 1 # y $end
$var wire 1 $ z $end
$upscope $end
$upscope $end
$enddefinitions $end
#0
$dumpvars
1'
0&
1%
0$
0#
0"
0!
$end
#20
1$
#40
1!
0'
0$
1#
#60
1$
#80
1!
1&
0'
0%
0$
0#
1"
#100
0!
1'
0&
1$
#120
1!
1&
0'
0$
1#
#140
0&
1$
