DSCO-3/Lab7/Q1/mux2to1.v
module mux2to1(w, s, f);
    input [1:0]w;
    input s;
    output reg f;
    always @(w or s)
    begin
        if(s==0)
        f=w[1];
        else 
        f=w[0];
        end
endmodule

DSCO-3/Lab7/Q1/mux2to1_tb.v
`timescale 1ns/1ns
`include "mux2to1.v"

module mux2to1_tb();
reg [1:0]w;
reg s;
wire f;

mux2to1 Mux2to1(w, s, f);
initial
begin
    
    $dumpfile("mux2to1.vcd");
    $dumpvars(0, mux2to1_tb);

    w=2'b00; s=1'b0; #20;
    w=2'b01; s=1'b0; #20;
    w=2'b10; s=1'b0; #20;
    w=2'b11; s=1'b0; #20;
    w=2'b00; s=1'b1; #20;
    w=2'b01; s=1'b1; #20;
    w=2'b10; s=1'b1; #20;
    w=2'b11; s=1'b1; #20;

    $display("Test complete.");
end
endmodule

DSCO-3/Lab7/Q1/mux2to1.vcd
$date
	Sat Oct 22 15:30:23 2022
$end
$version
	Icarus Verilog
$end
$timescale
	1ns
$end
$scope module mux2to1_tb $end
$var wire 1 ! f $end
$var reg 1 " s $end
$var reg 2 # w [1:0] $end
$scope module Mux2to1 $end
$var wire 1 " s $end
$var wire 2 $ w [1:0] $end
$var reg 1 ! f $end
$upscope $end
$upscope $end
$enddefinitions $end
#0
$dumpvars
b0 $
b0 #
0"
0!
$end
#20
b1 #
b1 $
#40
1!
b10 #
b10 $
#60
b11 #
b11 $
#80
0!
1"
b0 #
b0 $
#100
1!
b1 #
b1 $
#120
0!
b10 #
b10 $
#140
1!
b11 #
b11 $
