DSCO-3/Lab3/Q2/Q2B.v
module Q2B(A, B, C, D, f);
    input A, B, C, D;
    output f;
    assign f=(A|~B|D)&(~A|~B|C)&(~A|B|~C)&(~A|C|~D);
endmodule

DSCO-3/Lab3/Q2/Q2B_tb.v
`timescale 1ns/1ns
`include "Q2B.v"

module Q2B_tb();
reg A, B, C, D;
wire f;

Q2B q2b(A, B, C, D, f);
initial
begin
    
    $dumpfile("Q2B_tb.vcd");
    $dumpvars(0, Q2B_tb);

    A=1'b0; B=1'b0; C=1'b0; D=1'b0; #20;

    A=1'b0; B=1'b0; C=1'b0; D=1'b1; #20;

    A=1'b0; B=1'b0; C=1'b1; D=1'b0; #20;

    A=1'b0; B=1'b0; C=1'b1; D=1'b1; #20;

    A=1'b0; B=1'b1; C=1'b0; D=1'b0; #20;

    A=1'b0; B=1'b1; C=1'b0; D=1'b1; #20;

    A=1'b0; B=1'b1; C=1'b1; D=1'b0; #20;

    A=1'b0; B=1'b1; C=1'b1; D=1'b1; #20;

    A=1'b1; B=1'b0; C=1'b0; D=1'b0; #20;

    A=1'b1; B=1'b0; C=1'b0; D=1'b1; #20;

    A=1'b1; B=1'b0; C=1'b1; D=1'b0; #20;

    A=1'b1; B=1'b0; C=1'b1; D=1'b1; #20;

    A=1'b1; B=1'b1; C=1'b0; D=1'b0; #20;

    A=1'b1; B=1'b1; C=1'b0; D=1'b1; #20;

    A=1'b1; B=1'b1; C=1'b1; D=1'b0; #20;

    A=1'b1; B=1'b1; C=1'b1; D=1'b1; #20;

    $display("Test Complete");
end

endmodule

DSCO-3/Lab3/Q2/Q2B_tb.vcd
$date
	Sat Sep 10 15:17:24 2022
$end
$version
	Icarus Verilog
$end
$timescale
	1ns
$end
$scope module Q2B_tb $end
$var wire 1 ! f $end
$var reg 1 " A $end
$var reg 1 # B $end
$var reg 1 $ C $end
$var reg 1 % D $end
$scope module q2b $end
$var wire 1 " A $end
$var wire 1 # B $end
$var wire 1 $ C $end
$var wire 1 % D $end
$var wire 1 ! f $end
$upscope $end
$upscope $end
$enddefinitions $end
#0
$dumpvars
0%
0$
0#
0"
1!
$end
#20
1%
#40
0%
1$
#60
1%
#80
0!
0%
0$
1#
#100
1!
1%
#120
0!
0%
1$
#140
1!
1%
#160
0%
0$
0#
1"
#180
0!
1%
#200
0!
0%
1$
#220
1%
#240
0!
0%
0$
1#
#260
1%
#280
1!
0%
1$
#300
1%
