DSCO-3/Lab2/Q1/b/Q1b.v
module Q1b(X, Y, Z, lhs, rhs);
    input X, Y, Z;
    output lhs, rhs;
    assign lhs=X&(Y|Z);
    assign rhs=(X&Y)|(X&Z);
endmodule

DSCO-3/Lab2/Q1/b/Q1b_tb.v
`timescale 1ns/1ns
`include "Q1b.v"

module Q1b_tb();
reg X, Y, Z;
wire lhs, rhs;

Q1b q1b(X, Y, Z, lhs, rhs);
initial
begin

    $dumpfile("Q1b_tb.vcd");
    $dumpvars(0, Q1b_tb);

    X=1'b0; Y=1'b0; Z=1'b0;
    #20;

    X=1'b0; Y=1'b0; Z=1'b1;
    #20;

    X=1'b0; Y=1'b1; Z=1'b0;
    #20;

    X=1'b0; Y=1'b1; Z=1'b1;
    #20;

    X=1'b1; Y=1'b0; Z=1'b0;
    #20;

    X=1'b1; Y=1'b0; Z=1'b1;
    #20;

    X=1'b1; Y=1'b1; Z=1'b0;
    #20;

    X=1'b1; Y=1'b1; Z=1'b1;
    #20;

    $display("Test complete");
end

endmodule

DSCO-3/Lab2/Q1/b/Q1b_tb.vcd
$date
	Sat Sep  3 14:37:06 2022
$end
$version
	Icarus Verilog
$end
$timescale
	1ns
$end
$scope module Q1b_tb $end
$var wire 1 ! rhs $end
$var wire 1 " lhs $end
$var reg 1 # X $end
$var reg 1 $ Y $end
$var reg 1 % Z $end
$scope module q1b $end
$var wire 1 # X $end
$var wire 1 $ Y $end
$var wire 1 % Z $end
$var wire 1 " lhs $end
$var wire 1 ! rhs $end
$upscope $end
$upscope $end
$enddefinitions $end
#0
$dumpvars
0%
0$
0#
0"
0!
$end
#20
1%
#40
0%
1$
#60
1%
#80
0"
0%
0$
1#
#100
1"
1!
1%
#120
0%
1$
#140
1%
