DSCO-3/Lab9/Q1/DecomFA.v
module DecomFA(x,y,z,s,c);
input x,y,z;
output s,c;
HalfAdder h1(x,y,st,ct1);
HalfAdder h2(st,z, s, ct2);
assign c=ct1|ct2;
endmodule


module HalfAdder(x, y, s, c);
input x, y;
output s, c;
assign s=x^y;
assign c=x&y;
endmodule

DSCO-3/Lab9/Q1/DecomFA_tb.v
`timescale 1ns/1ns
`include "DecomFA.v"

module DecomFA_tb();
reg x,y,z;
wire s,c;

DecomFA ha(x,y,z,s,c);
initial
begin

	$dumpfile("DecomFA.vcd");
	$dumpvars(0, DecomFA_tb);

	x=1'b0; y=1'b0; z=1'b0; #20;
	x=1'b0; y=1'b0; z=1'b1; #20;
	x=1'b0; y=1'b1; z=1'b0; #20;
	x=1'b0; y=1'b1; z=1'b1; #20;	
	x=1'b1; y=1'b0; z=1'b0; #20;
	x=1'b1; y=1'b0; z=1'b1; #20;
	x=1'b1; y=1'b1; z=1'b0; #20;
	x=1'b1; y=1'b1; z=1'b1; #20;

	$display("Test complete.");
end
endmodule

DSCO-3/Lab9/Q1/DecomFA.vcd
$date
	Sat Nov  5 15:42:37 2022
$end
$version
	Icarus Verilog
$end
$timescale
	1ns
$end
$scope module DecomFA_tb $end
$var wire 1 ! s $end
$var wire 1 " c $end
$var reg 1 # x $end
$var reg 1 $ y $end
$var reg 1 % z $end
$scope module ha $end
$var wire 1 " c $end
$var wire 1 # x $end
$var wire 1 $ y $end
$var wire 1 % z $end
$var wire 1 & st $end
$var wire 1 ! s $end
$var wire 1 ' ct2 $end
$var wire 1 ( ct1 $end
$scope module h1 $end
$var wire 1 ( c $end
$var wire 1 & s $end
$var wire 1 # x $end
$var wire 1 $ y $end
$upscope $end
$scope module h2 $end
$var wire 1 ' c $end
$var wire 1 ! s $end
$var wire 1 & x $end
$var wire 1 % y $end
$upscope $end
$upscope $end
$upscope $end
$enddefinitions $end
#0
$dumpvars
0(
0'
0&
0%
0$
0#
0"
0!
$end
#20
1!
1%
#40
1&
0%
1$
#60
1"
0!
1'
1%
#80
0"
1!
0'
0%
0$
1#
#100
1"
0!
1'
1%
#120
0'
0&
1(
0%
1$
#140
1!
1%
