DSCO-3/Lab9/Q1/FullAdder.v
module FullAdder(x, y, z, s, c);
input x, y ,z;
output s, c;
s=x^y^z;
assign c=x&y|y&z|x&z;
endmodule

DSCO-3/Lab9/Q1/FullAdder_tb.v
`timescale 1ns/1ns
`include "FullAdder.v"

module FullAdder_tb();
reg x,y,z;
wire s,c;

FullAdder ha(x,y,z,s,c);
initial
begin

	$dumpfile("FullAdder.vcd");
	$dumpvars(0, FullAdder_tb);

	x=1'b0; y=1'b0; z=1'b0; #20;
	x=1'b0; y=1'b0; z=1'b1; #20;
	x=1'b0; y=1'b1; z=1'b0; #20;
	x=1'b0; y=1'b1; z=1'b1; #20;	
	x=1'b1; y=1'b0; z=1'b0; #20;
	x=1'b1; y=1'b0; z=1'b1; #20;
	x=1'b1; y=1'b1; z=1'b0; #20;
	x=1'b1; y=1'b1; z=1'b1; #20;

	$display("Test complete.");
end
endmodule

DSCO-3/Lab9/Q1/FullAdder.vcd
$date
	Sat Nov  5 15:10:12 2022
$end
$version
	Icarus Verilog
$end
$timescale
	1ns
$end
$scope module FullAdder_tb $end
$var wire 1 ! s $end
$var wire 1 " c $end
$var reg 1 # x $end
$var reg 1 $ y $end
$var reg 1 % z $end
$scope module ha $end
$var wire 1 " c $end
$var wire 1 ! s $end
$var wire 1 # x $end
$var wire 1 $ y $end
$var wire 1 % z $end
$upscope $end
$upscope $end
$enddefinitions $end
#0
$dumpvars
0%
0$
0#
0"
0!
$end
#20
1!
1%
#40
0%
1$
#60
1"
0!
1%
#80
0"
1!
0%
0$
1#
#100
1"
0!
1%
#120
0%
1$
#140
1!
1%
