DSCO-3/Lab2/Q2/q3/q3i.v
module q3i(x1, x2, x3, f);
    input x1, x2, x3;
    output f;
    nor(X1, x1, x1);
    nor(X3, x3, x3);
    nor(X1X2, x1, x2);
    nor(X1X3, X1, X3);
    nor(f, X1X3, X1X2);
endmodule

DSCO-3/Lab2/Q2/q3/q3i_tb.v
`timescale 1ns/1ns
`include "q3i.v"

module q3i_tb();
reg x1, x2, x3;
wire f;

q3i Q3i(x1, x2, x3, f);
initial
begin

    $dumpfile("q3i_tb.vcd");
    $dumpvars(0, q3i_tb);

    x1=1'b0; x2=1'b0; x3=1'b0;
    #20;

    x1=1'b0; x2=1'b0; x3=1'b1;
    #20;

    x1=1'b0; x2=1'b1; x3=1'b0;
    #20;

    x1=1'b0; x2=1'b1; x3=1'b1;
    #20;

    x1=1'b1; x2=1'b0; x3=1'b0;
    #20;

    x1=1'b1; x2=1'b0; x3=1'b1;
    #20;

    x1=1'b1; x2=1'b1; x3=1'b0;
    #20;

    x1=1'b1; x2=1'b1; x3=1'b1;
    #20;

    $display("Test complete");
end

endmodule

DSCO-3/Lab2/Q2/q3/q3i_tb.vcd
$date
	Sat Sep  3 16:00:05 2022
$end
$version
	Icarus Verilog
$end
$timescale
	1ns
$end
$scope module q3i_tb $end
$var wire 1 ! f $end
$var reg 1 " x1 $end
$var reg 1 # x2 $end
$var reg 1 $ x3 $end
$scope module Q3i $end
$var wire 1 % X1 $end
$var wire 1 & X1X2 $end
$var wire 1 ' X1X3 $end
$var wire 1 ( X3 $end
$var wire 1 ! f $end
$var wire 1 " x1 $end
$var wire 1 # x2 $end
$var wire 1 $ x3 $end
$upscope $end
$upscope $end
$enddefinitions $end
#0
$dumpvars
1(
0'
1&
1%
0$
0#
0"
0!
$end
#20
0(
1$
#40
1!
1(
0&
0$
1#
#60
0(
1$
#80
1(
0%
0$
0#
1"
#100
0!
1'
0(
1$
#120
1!
0'
1(
0$
1#
#140
0!
1'
0(
1$
