DSCO-3/Lab1/Add/AL1.v
module AL1(a, b, c, f1, f2);
    input a, b, c;
    output f1, f2;
    assign f1=(a&~c)+~(b^c);
    assign f2=((a|~b|c)&(a|b|~c)&(~a|b|~c));
endmodule

DSCO-3/Lab1/Add/AL1_tb.v
`timescale 1ns/1ns
`include "AL1.v"

module AL1_tb();
reg a, b, c;
wire f1, f2;

AL1 al1(a, b, c, f1, f2);
initial
begin

    $dumpfile("AL1_tb.vcd");
    $dumpvars(0, AL1_tb);

    a=1'b0; b=1'b0; c=1'b0; 
    #20;

    a=1'b0; b=1'b0; c=1'b1; 
    #20;
    
    a=1'b0; b=1'b1; c=1'b0; 
    #20;
    
    a=1'b0; b=1'b1; c=1'b1; 
    #20;
    
    a=1'b1; b=1'b0; c=1'b0; 
    #20;
    
    a=1'b1; b=1'b0; c=1'b1; 
    #20;
    
    a=1'b1; b=1'b1; c=1'b0; 
    #20;
    
    a=1'b1; b=1'b1; c=1'b1; 
    #20;
    
    
    $display("Test complete");
end

endmodule

DSCO-3/Lab1/Add/AL1_tb.vcd
$date
	Sat Aug 27 16:40:33 2022
$end
$version
	Icarus Verilog
$end
$timescale
	1ns
$end
$scope module AL1_tb $end
$var wire 1 ! f2 $end
$var wire 1 " f1 $end
$var reg 1 # a $end
$var reg 1 $ b $end
$var reg 1 % c $end
$scope module al1 $end
$var wire 1 # a $end
$var wire 1 $ b $end
$var wire 1 % c $end
$var wire 1 ! f2 $end
$var wire 1 " f1 $end
$upscope $end
$upscope $end
$enddefinitions $end
#0
$dumpvars
0%
0$
0#
1"
1!
$end
#20
0!
0"
1%
#40
0!
0%
1$
#60
1!
1"
1%
#80
0"
0%
0$
1#
#100
0!
0"
1%
#120
1!
1"
0%
1$
#140
1"
1%
