DSCO-3/Lab7/Q3/mux16to1.v
module mux16to1(w, s, f);
input[15:0]w;
input[3:0]s;
output f;
wire [1:0]o;

mux8to1 s1(w[7:0], s[2:0], o[0]);
mux8to1 s2(w[15:8], s[2:0], o[1]);
mux2to1 s5(o[1:0], s[3], f);
endmodule

module mux8to1(w,s,f);
input [7:0]w;
input [2:0]s;
output reg f;
always@(w or s)
begin
case(s)
0:f=w[0];
1:f=w[1];
2:f=w[2];
3:f=w[3];
4:f=w[4];
5:f=w[5];
6:f=w[6];
7:f=w[7];
endcase
end
endmodule

module mux2to1(w, s, f);
    input [1:0]w;
    input s;
    output reg f;
    always @(w or s)
    begin
        if(s==0)
        f=w[0];
        else 
        f=w[1];
        end
endmodule

DSCO-3/Lab7/Q3/mux16to1_tb.v
`timescale 1ns/1ns
`include "mux16to1.v"

module mux16to1_tb();
reg[15:0]w;
reg[3:0]s;
wire f;
integer i;

mux16to1 Mux16to1(w,s,f);
initial
begin

    $dumpfile("mux16to1.vcd");
    $dumpvars(0, mux16to1_tb);

    assign w=16'b1011011010100101;
    for(i=0; i<16; i=i+1) begin
        s = i; #10;
    end
    $display("Test complete.");
end
endmodule

DSCO-3/Lab7/Q3/mux16to1.vcd
$date
	Sat Oct 22 16:30:40 2022
$end
$version
	Icarus Verilog
$end
$timescale
	1ns
$end
$scope module mux16to1_tb $end
$var wire 1 ! f $end
$var reg 4 " s [3:0] $end
$var reg 16 # w [15:0] $end
$var integer 32 $ i [31:0] $end
$scope module Mux16to1 $end
$var wire 4 % s [3:0] $end
$var wire 16 & w [15:0] $end
$var wire 2 ' o [1:0] $end
$var wire 1 ! f $end
$scope module s1 $end
$var wire 3 ( s [2:0] $end
$var wire 8 ) w [7:0] $end
$var reg 1 * f $end
$upscope $end
$scope module s2 $end
$var wire 3 + s [2:0] $end
$var wire 8 , w [7:0] $end
$var reg 1 - f $end
$upscope $end
$scope module s5 $end
$var wire 1 . s $end
$var wire 2 / w [1:0] $end
$var reg 1 ! f $end
$upscope $end
$upscope $end
$upscope $end
$enddefinitions $end
#0
$dumpvars
b1 /
0.
0-
b10110110 ,
b0 +
1*
b10100101 )
b0 (
b1 '
b1011011010100101 &
b0 %
b0 $
b1011011010100101 #
b0 "
1!
$end
#10
0!
0*
b10 '
b10 /
1-
b1 (
b1 +
b1 "
b1 %
b1 $
#20
1!
b11 '
b11 /
1*
b10 (
b10 +
b10 "
b10 %
b10 $
#30
0!
0*
b0 '
b0 /
0-
b11 (
b11 +
b11 "
b11 %
b11 $
#40
b10 '
b10 /
1-
b100 (
b100 +
b100 "
b100 %
b100 $
#50
1!
b11 '
b11 /
1*
b101 (
b101 +
b101 "
b101 %
b101 $
#60
0!
0*
b0 '
b0 /
0-
b110 (
b110 +
b110 "
b110 %
b110 $
#70
1!
1*
b11 '
b11 /
1-
b111 (
b111 +
b111 "
b111 %
b111 $
#80
0!
b1 '
b1 /
0-
b0 (
b0 +
1.
b1000 "
b1000 %
b1000 $
#90
1!
0*
b10 '
b10 /
1-
b1 (
b1 +
b1001 "
b1001 %
b1001 $
#100
b11 '
b11 /
1*
b10 (
b10 +
b1010 "
b1010 %
b1010 $
#110
0!
0*
b0 '
b0 /
0-
b11 (
b11 +
b1011 "
b1011 %
b1011 $
#120
1!
b10 '
b10 /
1-
b100 (
b100 +
b1100 "
b1100 %
b1100 $
#130
b11 '
b11 /
1*
b101 (
b101 +
b1101 "
b1101 %
b1101 $
#140
0!
0*
b0 '
b0 /
0-
b110 (
b110 +
b1110 "
b1110 %
b1110 $
#150
1!
1*
b11 '
b11 /
1-
b111 (
b111 +
b1111 "
b1111 %
b1111 $
#160
b10000 $
