DSCO-3/Lab4/Q1/Q1.v
module 	Q1(A, B, C, D, f);
    input A, B, C, D;
    output f;
    nand(b, B, B);
    nand(d, D, D);
    nand(Ab, A, b);
    nand(Cd, C, d);
    nand(F, Ab, Cd);
    nand(f, F, F);
endmodule

DSCO-3/Lab4/Q1/Q1_tb.v
`timescale 1ns/1ns
`include "Q1.v"

module Q1_tb();
reg A, B, C, D;
wire f;

Q1 q1(A, B, C, D, f);
initial
begin
    
    $dumpfile("Q1_tb.vcd");
    $dumpvars(0, Q1_tb);

    A=1'b0; B=1'b0; C=1'b0; D=1'b0; #20;

    A=1'b0; B=1'b0; C=1'b0; D=1'b1; #20;

    A=1'b0; B=1'b0; C=1'b1; D=1'b0; #20;

    A=1'b0; B=1'b0; C=1'b1; D=1'b1; #20;

    A=1'b0; B=1'b1; C=1'b0; D=1'b0; #20;

    A=1'b0; B=1'b1; C=1'b0; D=1'b1; #20;

    A=1'b0; B=1'b1; C=1'b1; D=1'b0; #20;

    A=1'b0; B=1'b1; C=1'b1; D=1'b1; #20;

    A=1'b1; B=1'b0; C=1'b0; D=1'b0; #20;

    A=1'b1; B=1'b0; C=1'b0; D=1'b1; #20;

    A=1'b1; B=1'b0; C=1'b1; D=1'b0; #20;

    A=1'b1; B=1'b0; C=1'b1; D=1'b1; #20;

    A=1'b1; B=1'b1; C=1'b0; D=1'b0; #20;

    A=1'b1; B=1'b1; C=1'b0; D=1'b1; #20;

    A=1'b1; B=1'b1; C=1'b1; D=1'b0; #20;

    A=1'b1; B=1'b1; C=1'b1; D=1'b1; #20;

    $display("Test Complete");
end

endmodule

DSCO-3/Lab4/Q1/Q1_tb.vcd
$date
	Sat Sep 17 15:23:25 2022
$end
$version
	Icarus Verilog
$end
$timescale
	1ns
$end
$scope module Q1_tb $end
$var wire 1 ! f $end
$var reg 1 " A $end
$var reg 1 # B $end
$var reg 1 $ C $end
$var reg 1 % D $end
$scope module q1 $end
$var wire 1 " A $end
$var wire 1 & Ab $end
$var wire 1 # B $end
$var wire 1 $ C $end
$var wire 1 ' Cd $end
$var wire 1 % D $end
$var wire 1 ( F $end
$var wire 1 ) b $end
$var wire 1 * d $end
$var wire 1 ! f $end
$upscope $end
$upscope $end
$enddefinitions $end
#0
$dumpvars
1*
1)
0(
1'
1&
0%
0$
0#
0"
1!
$end
#20
0*
1%
#40
0!
1(
0'
1*
0%
1$
#60
1!
0(
1'
0*
1%
#80
1*
0)
0%
0$
1#
#100
0*
1%
#120
0!
1(
0'
1*
0%
1$
#140
1!
0(
1'
0*
1%
#160
0!
1(
0&
1*
1)
0%
0$
0#
1"
#180
0*
1%
#200
0'
1*
0%
1$
#220
1'
0*
1%
#240
1!
0(
1&
1*
0)
0%
0$
1#
#260
0*
1%
#280
0!
1(
0'
1*
0%
1$
#300
1!
0(
1'
0*
1%
