DSCO-3/Lab2/Q2/q1/q1i.v
module q1i(A, B, C, Y);
    input A, B, C;
    output Y;
    assign Y=(A&B)|(A&C)|(B&C);
endmodule

DSCO-3/Lab2/Q2/q1/q1i_tb.v
`timescale 1ns/1ns
`include "q1i.v"

module q1i_tb();
reg A, B, C;
wire Y;

q1i Q1i(A, B, C, Y);
initial
begin

    $dumpfile("q1i_tb.vcd");
    $dumpvars(0, q1i_tb);

    A=1'b0; B=1'b0; C=1'b0;
    #20;

    A=1'b0; B=1'b0; C=1'b1;
    #20;

    A=1'b0; B=1'b1; C=1'b0;
    #20;

    A=1'b0; B=1'b1; C=1'b1;
    #20;

    A=1'b1; B=1'b0; C=1'b0;
    #20;

    A=1'b1; B=1'b0; C=1'b1;
    #20;

    A=1'b1; B=1'b1; C=1'b0;
    #20;

    A=1'b1; B=1'b1; C=1'b1;
    #20;

    $display("Test complete");
end

endmodule

DSCO-3/Lab2/Q2/q1/q1i_tb.vcd
$date
	Sat Sep  3 15:06:47 2022
$end
$version
	Icarus Verilog
$end
$timescale
	1ns
$end
$scope module q1i_tb $end
$var wire 1 ! Y $end
$var reg 1 " A $end
$var reg 1 # B $end
$var reg 1 $ C $end
$scope module Q1i $end
$var wire 1 " A $end
$var wire 1 # B $end
$var wire 1 $ C $end
$var wire 1 ! Y $end
$upscope $end
$upscope $end
$enddefinitions $end
#0
$dumpvars
0$
0#
0"
0!
$end
#20
1$
#40
0$
1#
#60
1!
1$
#80
0!
0$
0#
1"
#100
1!
1$
#120
0$
1#
#140
1$
