DSCO-3/Lab2/Q1/c/Q1c.v
module Q1c(X, Y, Z, lhs, rhs);
    input X, Y, Z;
    output lhs, rhs;
    assign lhs=X|(Y&Z);
    assign rhs=(X|Y)&(X|Z);
endmodule

DSCO-3/Lab2/Q1/c/Q1c_tb.v
`timescale 1ns/1ns
`include "Q1c.v"

module Q1c_tb();
reg X, Y, Z;
wire lhs, rhs;

Q1c q1c(X, Y, Z, lhs, rhs);
initial
begin

    $dumpfile("Q1c_tb.vcd");
    $dumpvars(0, Q1c_tb);

    X=1'b0; Y=1'b0; Z=1'b0;
    #20;

    X=1'b0; Y=1'b0; Z=1'b1;
    #20;

    X=1'b0; Y=1'b1; Z=1'b0;
    #20;

    X=1'b0; Y=1'b1; Z=1'b1;
    #20;

    X=1'b1; Y=1'b0; Z=1'b0;
    #20;

    X=1'b1; Y=1'b0; Z=1'b1;
    #20;

    X=1'b1; Y=1'b1; Z=1'b0;
    #20;

    X=1'b1; Y=1'b1; Z=1'b1;
    #20;

    $display("Test complete");
end

endmodule

DSCO-3/Lab2/Q1/c/Q1c_tb.vcd
$date
	Sat Sep  3 14:42:48 2022
$end
$version
	Icarus Verilog
$end
$timescale
	1ns
$end
$scope module Q1c_tb $end
$var wire 1 ! rhs $end
$var wire 1 " lhs $end
$var reg 1 # X $end
$var reg 1 $ Y $end
$var reg 1 % Z $end
$scope module q1c $end
$var wire 1 # X $end
$var wire 1 $ Y $end
$var wire 1 % Z $end
$var wire 1 " lhs $end
$var wire 1 ! rhs $end
$upscope $end
$upscope $end
$enddefinitions $end
#0
$dumpvars
0%
0$
0#
0"
0!
$end
#20
1%
#40
0%
1$
#60
1"
1!
1%
#80
0%
0$
1#
#100
1%
#120
0%
1$
#140
1%
