DSCO-3/Lab1/Q1/Q1i.v
module Q1i(a, b, c, d, f);
    input a, b, c, d;
    output f;
    and(l, a, b);
    or(m, l, c);
    not(n, m);
    and(o, d, n);
    or(p, d, m);
    and(f, o, p);
endmodule

DSCO-3/Lab1/Q1/Q1i_tb.v
`timescale 1ns/1ns
`include "Q1i.v"

module Q1i_tb();
reg a, b, c, d;
wire f;

Q1i q1i(a, b, c, d, f);
initial
begin

    $dumpfile("Q1i_tb.vcd");
    $dumpvars(0, Q1i_tb);

    a=1'b0; b=1'b0; c=1'b0; d=1'b0;
    #20;

    a=1'b0; b=1'b0; c=1'b0; d=1'b1;
    #20;
    
    a=1'b0; b=1'b0; c=1'b1; d=1'b0;
    #20;
    
    a=1'b0; b=1'b0; c=1'b1; d=1'b1;
    #20;
    
    a=1'b0; b=1'b1; c=1'b0; d=1'b0;
    #20;
    
    a=1'b0; b=1'b1; c=1'b0; d=1'b1;
    #20;
    
    a=1'b0; b=1'b1; c=1'b1; d=1'b0;
    #20;
    
    a=1'b0; b=1'b1; c=1'b1; d=1'b1;
    #20;
    
    a=1'b1; b=1'b0; c=1'b0; d=1'b0;
    #20;
    
    a=1'b1; b=1'b0; c=1'b0; d=1'b1;
    #20;
    
    a=1'b1; b=1'b0; c=1'b1; d=1'b0;
    #20;
    
    a=1'b1; b=1'b0; c=1'b1; d=1'b1;
    #20;
    
    a=1'b1; b=1'b1; c=1'b0; d=1'b0;
    #20;
    
    a=1'b1; b=1'b1; c=1'b0; d=1'b1;
    #20;
    
    a=1'b1; b=1'b1; c=1'b1; d=1'b0;
    #20;
    
    a=1'b1; b=1'b1; c=1'b1; d=1'b1;
    #20;
    
    $display("Test complete");
end

endmodule

DSCO-3/Lab1/Q1/Q1i_tb.vcd
$date
	Sat Aug 27 15:41:53 2022
$end
$version
	Icarus Verilog
$end
$timescale
	1ns
$end
$scope module Q1i_tb $end
$var wire 1 ! f $end
$var reg 1 " a $end
$var reg 1 # b $end
$var reg 1 $ c $end
$var reg 1 % d $end
$scope module q1i $end
$var wire 1 " a $end
$var wire 1 # b $end
$var wire 1 $ c $end
$var wire 1 % d $end
$var wire 1 ! f $end
$var wire 1 & l $end
$var wire 1 ' m $end
$var wire 1 ( n $end
$var wire 1 ) o $end
$var wire 1 * p $end
$upscope $end
$upscope $end
$enddefinitions $end
#0
$dumpvars
0*
0)
1(
0'
0&
0%
0$
0#
0"
0!
$end
#20
1!
1)
1*
1%
#40
0!
0(
0)
1'
0%
1$
#60
1%
#80
1(
0*
0'
0%
0$
1#
#100
1!
1)
1*
1%
#120
0!
0(
0)
1'
0%
1$
#140
1%
#160
1(
0*
0'
0%
0$
0#
1"
#180
1!
1)
1*
1%
#200
0!
0(
0)
1'
0%
1$
#220
1%
#240
1&
0%
0$
1#
#260
1%
#280
0%
1$
#300
1%
